runwayml/__init__.py
runwayml/_base_client.py
runwayml/_client.py
runwayml/_compat.py
runwayml/_constants.py
runwayml/_exceptions.py
runwayml/_files.py
runwayml/_models.py
runwayml/_qs.py
runwayml/_resource.py
runwayml/_response.py
runwayml/_streaming.py
runwayml/_types.py
runwayml/_version.py
runwayml/py.typed
runwayml/_utils/__init__.py
runwayml/_utils/_compat.py
runwayml/_utils/_datetime_parse.py
runwayml/_utils/_logs.py
runwayml/_utils/_proxy.py
runwayml/_utils/_reflection.py
runwayml/_utils/_resources_proxy.py
runwayml/_utils/_streams.py
runwayml/_utils/_sync.py
runwayml/_utils/_transform.py
runwayml/_utils/_typing.py
runwayml/_utils/_utils.py
runwayml/lib/.keep
runwayml/lib/polling.py
runwayml/resources/__init__.py
runwayml/resources/character_performance.py
runwayml/resources/image_to_video.py
runwayml/resources/organization.py
runwayml/resources/sound_effect.py
runwayml/resources/speech_to_speech.py
runwayml/resources/tasks.py
runwayml/resources/text_to_image.py
runwayml/resources/text_to_speech.py
runwayml/resources/text_to_video.py
runwayml/resources/uploads.py
runwayml/resources/video_to_video.py
runwayml/resources/voice_dubbing.py
runwayml/resources/voice_isolation.py
runwayml/types/__init__.py
runwayml/types/character_performance_create_params.py
runwayml/types/character_performance_create_response.py
runwayml/types/image_to_video_create_params.py
runwayml/types/image_to_video_create_response.py
runwayml/types/organization_retrieve_response.py
runwayml/types/organization_retrieve_usage_params.py
runwayml/types/organization_retrieve_usage_response.py
runwayml/types/sound_effect_create_params.py
runwayml/types/sound_effect_create_response.py
runwayml/types/speech_to_speech_create_params.py
runwayml/types/speech_to_speech_create_response.py
runwayml/types/task_retrieve_response.py
runwayml/types/text_to_image_create_params.py
runwayml/types/text_to_image_create_response.py
runwayml/types/text_to_speech_create_params.py
runwayml-4.3.0.dist-info/METADATA
runwayml-4.3.0.dist-info/WHEEL
runwayml-4.3.0.dist-info/licenses/LICENSE
runwayml-4.3.0.dist-info/RECORD
